Calculator/Calculator.py
Calculator/__init__.py
intotherain-0.0.2.dist-info/METADATA
intotherain-0.0.2.dist-info/WHEEL
intotherain-0.0.2.dist-info/top_level.txt
intotherain-0.0.2.dist-info/RECORD
