Metadata-Version: 2.1
Name: intotherain
Version: 0.0.2
Summary: Basic Calculator
Home-page: https://github.com/timetobye/Make_pypi_practice
Author: time_to_bye
Author-email: secret@secret.com
License: UNKNOWN
Keywords: practice,temp_practice
Platform: UNKNOWN
Requires-Python: >=3
